nrtk_jatic/__init__.py
nrtk_jatic/py.typed
nrtk_jatic-0.5.0.dist-info/LICENSE
nrtk_jatic-0.5.0.dist-info/METADATA
nrtk_jatic-0.5.0.dist-info/WHEEL
nrtk_jatic-0.5.0.dist-info/entry_points.txt
nrtk_jatic-0.5.0.dist-info/RECORD
