Metadata-Version: 2.1
Name: nrtk-jatic
Version: 0.5.0
Summary: A wrapper for nrtk to comply with maite protocols.
License: Apache-2.0
Author: Kitware, Inc.
Author-email: nrtk@kitware.com
Requires-Python: >=3.9,<4.0
Classifier: Development Status :: 3 - Alpha
Classifier: Intended Audience :: Developers
Classifier: Intended Audience :: Science/Research
Classifier: License :: OSI Approved :: Apache Software License
Classifier: Operating System :: MacOS :: MacOS X
Classifier: Operating System :: Unix
Classifier: Programming Language :: Python :: 3
Classifier: Programming Language :: Python :: 3.9
Classifier: Programming Language :: Python :: 3.10
Classifier: Programming Language :: Python :: 3.11
Classifier: Programming Language :: Python :: 3.12
Classifier: Programming Language :: Python :: 3.13
Provides-Extra: graphics
Provides-Extra: headless
Provides-Extra: maite-cpu
Provides-Extra: pybsm
Provides-Extra: tools
Requires-Dist: fastapi (>=0.110.0,<0.111.0)
Requires-Dist: httpx (>=0.27.0,<0.28.0)
Requires-Dist: kwcoco (>=0.2.18) ; extra == "tools"
Requires-Dist: maite (>=0.7.1,<0.8.0)
Requires-Dist: nrtk (>=0.20.0) ; extra == "pybsm" or extra == "graphics" or extra == "headless"
Requires-Dist: nrtk[graphics] (>=0.20.0) ; extra == "graphics"
Requires-Dist: nrtk[headless] (>=0.20.0) ; extra == "headless"
Requires-Dist: nrtk[pybsm] (>=0.20.0) ; extra == "pybsm"
Requires-Dist: numpy (>=1.22,<2.0) ; python_version >= "3.9" and python_version < "3.13"
Requires-Dist: pydantic (>=2.6.4)
Requires-Dist: pydantic_settings (>=2.2.1)
Requires-Dist: pyyaml (>=6.0.1)
Requires-Dist: responses (>=0.25.0)
Requires-Dist: torch (>=1.7,!=1.12.0) ; extra == "maite-cpu"
Requires-Dist: torchvision (>=0.10.0) ; extra == "maite-cpu"
Requires-Dist: uvicorn (>=0.29.0,<0.30.0)
Project-URL: Documentation, https://nrtk-jatic.readthedocs.io/
